.coveragerc
GPL.txt
LICENSE.txt
MANIFEST.in
README.rst
requirements.txt
setup.py
test.py
ParamComparison.egg-info/PKG-INFO
ParamComparison.egg-info/SOURCES.txt
ParamComparison.egg-info/dependency_links.txt
ParamComparison.egg-info/requires.txt
ParamComparison.egg-info/top_level.txt
paramcomparison/__init__.py
paramcomparison/readers.py
paramcomparison/writers.py