Metadata-Version: 1.0
Name: ParamComparison
Version: 0.2.2
Summary: Parameter Comparison Table Generator
Home-page: http://paramcomp.topbug.net
Author: Hong Xu
Author-email: hong@topbug.net
License: LGPLv3+
Platform: UNKNOWN
